agi_tools/__init__.py
agi_tools/mail/__init__.py
agi_tools/semaphore/__init__.py
agi_tools/spark/__init__.py
agi_tools/teams/__init__.py
agi_tools/tools/__init__.py
agi_tools-0.1.7.dist-info/METADATA
agi_tools-0.1.7.dist-info/WHEEL
agi_tools-0.1.7.dist-info/entry_points.txt
agi_tools-0.1.7.dist-info/RECORD
