Metadata-Version: 2.4
Name: agi-tools
Version: 0.1.7
Summary: Biblioteca Python para integração com Spark, Data Lake, envio de e-mails corporativos via Microsoft Graph API e manipulação centralizada de configurações. Ideal para projetos de dados que exigem automação, controle de métricas e comunicação corporativa.
Author-email: Moacyr Rodrigues Neto <moacyr.neto@agi.com.br>
License-Expression: MIT
Requires-Python: >=3.9
Requires-Dist: msal
Requires-Dist: pymsteams
Requires-Dist: python-dateutil
Requires-Dist: pytz
Requires-Dist: tomli
